app/__init__.py
app/client.ipynb
app/main.py
app/server.py
zeitkapsel_api-0.1.0.dist-info/METADATA
zeitkapsel_api-0.1.0.dist-info/WHEEL
zeitkapsel_api-0.1.0.dist-info/RECORD
