Metadata-Version: 2.1
Name: zeitkapsel-api
Version: 0.1.0
Summary: 
Author: Your Name
Author-email: you@example.com
Requires-Python: >=3.11,<4.0
Classifier: Programming Language :: Python :: 3
Classifier: Programming Language :: Python :: 3.11
Classifier: Programming Language :: Python :: 3.12
Requires-Dist: aiosqlite (>=0.20.0,<0.21.0)
Requires-Dist: langchain (>=0.2.11,<0.3.0)
Requires-Dist: langchain-cli (>=0.0.22,<0.0.23)
Requires-Dist: langchain-openai (>=0.1.6,<0.2.0)
Requires-Dist: langgraph (==0.1.15)
Requires-Dist: langserve[server] (>=0.0.30)
Requires-Dist: psycopg (>=3.2.1,<4.0.0)
Requires-Dist: psycopg2-binary (>=2.9.9,<3.0.0)
Requires-Dist: pydantic (>=2.7.4,<3.0.0)
Requires-Dist: python-dotenv (>=1.0.1,<2.0.0)
Requires-Dist: uvicorn (>=0.23.2,<0.24.0)
